[
  {
    "ExportType": "Material",
    "ExportValue": {
      "Metallic": {
        "/Engine/EngineMaterials/DefaultDiffuse": null
      },
      "Specular": {
        "/Engine/EngineMaterials/Good64x64TilingNoiseHighFreq": null
      },
      "Anisotropy": {
        "/Game/Characters/Campers/Textures/Vomit/T_Vomit01_N": null
      },
      "Normal": {
        "Parent": {
          "ExpressionName": {
            "String": "MaterialExpressionGetMaterialAttributes"
          }
        },
        "UseConstant": false,
        "Constant": {
          "X": 0.0,
          "Y": 0.0,
          "Z": 0.0
        }
      },
      "Tangent": {
        "Parent": {
          "ExpressionName": {
            "String": "MaterialExpressionGetMaterialAttributes"
          }
        },
        "UseConstant": false,
        "Constant": {
          "X": 0.0,
          "Y": 0.0,
          "Z": 0.0
        }
      },
      "EmissiveColor": {
        "Parent": {
          "ExpressionName": {
            "String": "MaterialExpressionGetMaterialAttributes"
          }
        },
        "UseConstant": false,
        "Constant": {
          "R": 0,
          "G": 0,
          "B": 0,
          "A": 0,
          "Hex": "000000"
        }
      },
      "WorldPositionOffset": {
        "Parent": {
          "ExpressionName": {
            "String": "MaterialExpressionGetMaterialAttributes"
          }
        },
        "UseConstant": false,
        "Constant": {
          "X": 0.0,
          "Y": 0.0,
          "Z": 0.0
        }
      },
      "Refraction": {
        "/Game/Materials/MaterialFunctions/Environment/MF_Material": null
      },
      "MaterialAttributes": {
        "/Engine/EngineMaterials/BlendFunc_DefBase": null
      },
      "PixelDepthOffset": {
        "/Game/Textures/Environment/_Common/Defaults/T_MRH_Default": null
      },
      "ShadingModelFromMaterialExpression": {
        "OutputIndex": 27
      },
      "bUsedWithSkeletalMesh": true,
      "bUsedWithStaticLighting": true,
      "bUsedWithInstancedStaticMeshes": true,
      "bAutomaticallySetUsageInEditor": false,
      "StateId": "0A8F92854CBEF7FEE9940BA111E277E0",
      "MaxDisplacement": 10.0,
      "CachedExpressionData": {
        "Parameters": {
          "Entries": {
            "NameHashes": [
              306973994443117153,
              443498317581505812,
              950992661302148043,
              989883415187597061,
              1115986713387641917,
              1201889017883843311,
              1284847081464955958,
              1301221294470682031,
              1557503403865896282,
              1575961949748482175,
              1596637639891226948,
              1726532113807391456,
              2127517526637479799,
              2177110987862561912,
              2190422024312069961,
              2321219887023102178,
              2450613621330263263,
              2489002538054161922,
              2914396828406378827,
              2941347292332804434,
              3192667243898537791,
              3294501651284707796,
              3370344523696098492,
              3392345604932720041,
              3521804494479231701,
              3690555642836926936,
              3891312254753352339,
              4051743926679508469,
              4125117869975066150,
              4335768296610277011,
              4484613503980798998,
              4514415099010930137,
              4594294583106714585,
              4616562210736049166,
              4779914027733138181,
              4840008367560841127,
              5052894396075968285,
              5224145262374858800,
              5373217452327527277,
              5644697285901670108,
              5792620731907687137,
              5798691535098793656,
              5877135138973004762,
              6096218115960958577,
              6203491026684189460,
              6226934856811249152,
              6308487713591156934,
              6615800340583810074,
              6616884334127517513,
              6684997229760216449,
              6716638179665174624,
              6834175566651832517,
              6844010527955396351,
              6858938754192155488,
              7178050848241010699,
              7267285484110246043,
              7553201608726239400,
              7613611307148592814,
              7676919229188795519,
              7684964684824581901,
              7973310891996083283,
              8241200164885323229,
              8268393396989276524,
              8931857770186878099,
              8962594342829480848,
              9086674602805614852,
              9210914208149213253,
              9230817365160103195,
              9241363615764591948,
              9319150672196728342,
              9328339845075407222,
              9411114019420439000,
              9590356976266990507,
              9627595397757473594,
              9721205416602206127,
              9976421207098966764,
              9980091055762844233,
              10258923844658405196,
              10401744394493843957,
              10620897943360653811,
              10770577894898404384,
              10796333269438592089,
              10926839830276583538,
              11058693766691052041,
              11449037389117682031,
              11486188116992906263,
              11591322375650610213,
              11649501631232830426,
              11677405801477206891,
              11733733674280395237,
              11758033998135654853,
              11814282092690906018,
              12166606847272946924,
              12433087988760211092,
              12455502742921325568,
              12641114031217146339,
              12853014366858075414,
              13119648536237829734,
              13331683771392156266,
              13562825895486949498,
              13722552935344633005,
              14023964523075892713,
              14050175619136938700,
              14055350899467841899,
              14133261818466732705,
              14172097952831641065,
              14362021425833360053,
              14389503172284484141,
              14444632299042076728,
              14627206798852097229,
              14839190913380867957,
              14942007118077334553,
              15010956102484412782,
              15091978116683952725,
              15179969726570141349,
              15235737848866081735,
              15276424501027740892,
              15340003634335429968,
              15369918478702835629,
              15371808149321996007,
              15433303832576480086,
              15496442685746616440,
              15757367725954018146,
              15911249125667208732,
              15941298948362317245,
              15998222917134117710,
              16523527952969663601,
              16599363702163672366,
              16654546661840614998,
              17003790970301418264,
              17192486000587660216,
              17218356368102714524,
              17277362403778633186,
              17282728076024324196,
              17437381768936582156,
              17503415841620058552,
              17507236197070552615,
              17642682638443675945,
              17815296418984816593,
              18001047826823800727,
              18279101692816316934
            ],
            "ParameterInfos": [
              {
                "Name": "018_FadeRadius",
                "Association": "GlobalParameter",
                "Index": -1
              },
              {
                "Name": "|     Adjustment Hue     .",
                "Association": "GlobalParameter",
                "Index": -1
              },
              {
                "Name": "Height Map Black Level",
                "Association": "GlobalParameter",
                "Index": -1
              },
              {
                "Name": "|     Specular Value",
                "Association": "GlobalParameter",
                "Index": -1
              },
              {
                "Name": "|     Roughness Map Tiling     .",
                "Association": "GlobalParameter",
                "Index": -1
              },
              {
                "Name": "Atl_EmissiveMultiplier",
                "Association": "GlobalParameter",
                "Index": -1
              },
              {
                "Name": "BorderThresholdLow",
                "Association": "GlobalParameter",
                "Index": -1
              },
              {
                "Name": "|     U Tiling",
                "Association": "GlobalParameter",
                "Index": -1
              },
              {
                "Name": "|     U Offset Tint",
                "Association": "GlobalParameter",
                "Index": -1
              },
              {
                "Name": "42 - GradientHardness",
                "Association": "GlobalParameter",
                "Index": -1
              },
              {
                "Name": "|     Rotation Center          .",
                "Association": "GlobalParameter",
                "Index": -1
              },
              {
                "Name": "Atl_Roughness",
                "Association": "GlobalParameter",
                "Index": -1
              },
              {
                "Name": "|     Normal Map Tiling     .",
                "Association": "GlobalParameter",
                "Index": -1
              },
              {
                "Name": "|     V Offset",
                "Association": "GlobalParameter",
                "Index": -1
              },
              {
                "Name": "UV Channel",
                "Association": "GlobalParameter",
                "Index": -1
              },
              {
                "Name": "UV Channel     .",
                "Association": "GlobalParameter",
                "Index": -1
              },
              {
                "Name": "|     BaseColor Tint Intensity",
                "Association": "GlobalParameter",
                "Index": -1
              },
              {
                "Name": "|     BaseColor Intensity     .",
                "Association": "GlobalParameter",
                "Index": -1
              },
              {
                "Name": "UltraLow_Spec",
                "Association": "GlobalParameter",
                "Index": -1
              },
              {
                "Name": "|     Roughness Map Tiling",
                "Association": "GlobalParameter",
                "Index": -1
              },
              {
                "Name": "BorderIntensity",
                "Association": "GlobalParameter",
                "Index": -1
              },
              {
                "Name": "UV Tiling Master     .",
                "Association": "GlobalParameter",
                "Index": -1
              },
              {
                "Name": "|     BaseColor Saturation",
                "Association": "GlobalParameter",
                "Index": -1
              },
              {
                "Name": "|     BaseColor Hue",
                "Association": "GlobalParameter",
                "Index": -1
              },
              {
                "Name": "|     V Offset ....",
                "Association": "GlobalParameter",
                "Index": -1
              },
              {
                "Name": "|     Specular Map Tiling",
                "Association": "GlobalParameter",
                "Index": -1
              },
              {
                "Name": "UV Tiling Master       .",
                "Association": "GlobalParameter",
                "Index": -1
              },
              {
                "Name": "|     Normal Map Detail Intensity",
                "Association": "GlobalParameter",
                "Index": -1
              },
              {
                "Name": "|     Adjustment Saturation     .",
                "Association": "GlobalParameter",
                "Index": -1
              },
              {
                "Name": "42 - BoundsMultiplier",
                "Association": "GlobalParameter",
                "Index": -1
              },
              {
                "Name": "|     Roughness Map Black Level",
                "Association": "GlobalParameter",
                "Index": -1
              },
              {
                "Name": "|     Occlusion Map Contrast",
                "Association": "GlobalParameter",
                "Index": -1
              },
              {
                "Name": "Emissive_Tile_Y",
                "Association": "GlobalParameter",
                "Index": -1
              },
              {
                "Name": "018_FadeRadiusDistance",
                "Association": "GlobalParameter",
                "Index": -1
              },
              {
                "Name": "|     Roughness Map Detail Black Level",
                "Association": "GlobalParameter",
                "Index": -1
              },
              {
                "Name": "SpecularValue",
                "Association": "GlobalParameter",
                "Index": -1
              },
              {
                "Name": "EndLocation_WorldSpace",
                "Association": "GlobalParameter",
                "Index": -1
              },
              {
                "Name": "Emissive_Tile",
                "Association": "GlobalParameter",
                "Index": -1
              },
              {
                "Name": "|     Normal Map Detail Tiling",
                "Association": "GlobalParameter",
                "Index": -1
              },
              {
                "Name": "|     Intensity ....",
                "Association": "GlobalParameter",
                "Index": -1
              },
              {
                "Name": "UV Channel       .",
                "Association": "GlobalParameter",
                "Index": -1
              },
              {
                "Name": "|     U Offset     .",
                "Association": "GlobalParameter",
                "Index": -1
              },
              {
                "Name": "|     Roughness Map Detail Tiling Multiplier",
                "Association": "GlobalParameter",
                "Index": -1
              },
              {
                "Name": "|     U Tiling Tint",
                "Association": "GlobalParameter",
                "Index": -1
              },
              {
                "Name": "|     U Tiling          .",
                "Association": "GlobalParameter",
                "Index": -1
              },
              {
                "Name": "MaskIntensity",
                "Association": "GlobalParameter",
                "Index": -1
              },
              {
                "Name": "|     Occlusion Map Black Level",
                "Association": "GlobalParameter",
                "Index": -1
              },
              {
                "Name": "Atl_Metallic",
                "Association": "GlobalParameter",
                "Index": -1
              },
              {
                "Name": "|     WS Blend Contrast     .",
                "Association": "GlobalParameter",
                "Index": -1
              },
              {
                "Name": "|     Roughness Map Contrast",
                "Association": "GlobalParameter",
                "Index": -1
              },
              {
                "Name": "|     U Offset       .",
                "Association": "GlobalParameter",
                "Index": -1
              },
              {
                "Name": "|     U Tiling       .",
                "Association": "GlobalParameter",
                "Index": -1
              },
              {
                "Name": "|     V Tiling ....",
                "Association": "GlobalParameter",
                "Index": -1
              },
              {
                "Name": "DIssolveBorderGreenChannel",
                "Association": "GlobalParameter",
                "Index": -1
              },
              {
                "Name": "UltraLow_Rough",
                "Association": "GlobalParameter",
                "Index": -1
              },
              {
                "Name": "|     Rotation Center Tint",
                "Association": "GlobalParameter",
                "Index": -1
              },
              {
                "Name": "|     Rotation Center       .",
                "Association": "GlobalParameter",
                "Index": -1
              },
              {
                "Name": "|     Roughness Intensity",
                "Association": "GlobalParameter",
                "Index": -1
              },
              {
                "Name": "|     Rotation Tint",
                "Association": "GlobalParameter",
                "Index": -1
              },
              {
                "Name": "|     Previous Normals Map Intensity    .",
                "Association": "GlobalParameter",
                "Index": -1
              },
              {
                "Name": "Min A",
                "Association": "GlobalParameter",
                "Index": -1
              },
              {
                "Name": "DissolveTexture_TileX",
                "Association": "GlobalParameter",
                "Index": -1
              },
              {
                "Name": "|     Roughness Map Intensity     .",
                "Association": "GlobalParameter",
                "Index": -1
              },
              {
                "Name": "|     Roughness Map Detail Intensity",
                "Association": "GlobalParameter",
                "Index": -1
              },
              {
                "Name": "|     Opacity Intensity",
                "Association": "GlobalParameter",
                "Index": -1
              },
              {
                "Name": "|     Material 1 Intensity",
                "Association": "GlobalParameter",
                "Index": -1
              },
              {
                "Name": "42 - InverseDissolve",
                "Association": "GlobalParameter",
                "Index": -1
              },
              {
                "Name": "|     Roughness Map Detail Contrast",
                "Association": "GlobalParameter",
                "Index": -1
              },
              {
                "Name": "UV Tiling Master",
                "Association": "GlobalParameter",
                "Index": -1
              },
              {
                "Name": "|     Tint Opacity Map Intensity",
                "Association": "GlobalParameter",
                "Index": -1
              },
              {
                "Name": "|     BaseColor Tint Map Tiling",
                "Association": "GlobalParameter",
                "Index": -1
              },
              {
                "Name": "|     U Offset          .",
                "Association": "GlobalParameter",
                "Index": -1
              },
              {
                "Name": "|     Rotation Center     .",
                "Association": "GlobalParameter",
                "Index": -1
              },
              {
                "Name": "42 - Height",
                "Association": "GlobalParameter",
                "Index": -1
              },
              {
                "Name": "|     Roughness Map Contrast     .",
                "Association": "GlobalParameter",
                "Index": -1
              },
              {
                "Name": "|     V Offset          .",
                "Association": "GlobalParameter",
                "Index": -1
              },
              {
                "Name": "|     Roughness Map Black Level     .",
                "Association": "GlobalParameter",
                "Index": -1
              },
              {
                "Name": "MaxBorderGlow",
                "Association": "GlobalParameter",
                "Index": -1
              },
              {
                "Name": "|     Normal Map Intensity     .",
                "Association": "GlobalParameter",
                "Index": -1
              },
              {
                "Name": "UV Tiling Master ....",
                "Association": "GlobalParameter",
                "Index": -1
              },
              {
                "Name": "|     Tint Opacity Map Tiling",
                "Association": "GlobalParameter",
                "Index": -1
              },
              {
                "Name": "|     WS Opacity     .",
                "Association": "GlobalParameter",
                "Index": -1
              },
              {
                "Name": "|     Occlusion Intensity",
                "Association": "GlobalParameter",
                "Index": -1
              },
              {
                "Name": "42 - Base Offset",
                "Association": "GlobalParameter",
                "Index": -1
              },
              {
                "Name": "|     Material 1 Black Level",
                "Association": "GlobalParameter",
                "Index": -1
              },
              {
                "Name": "|     U Tiling     .",
                "Association": "GlobalParameter",
                "Index": -1
              },
              {
                "Name": "Speed Y",
                "Association": "GlobalParameter",
                "Index": -1
              },
              {
                "Name": "|     V Tiling       .",
                "Association": "GlobalParameter",
                "Index": -1
              },
              {
                "Name": "|     Tint Opacity Map Contrast",
                "Association": "GlobalParameter",
                "Index": -1
              },
              {
                "Name": "Height Map Contrast",
                "Association": "GlobalParameter",
                "Index": -1
              },
              {
                "Name": "|     Roughness Intensity     .",
                "Association": "GlobalParameter",
                "Index": -1
              },
              {
                "Name": "|     BaseColor Map Tiling     .",
                "Association": "GlobalParameter",
                "Index": -1
              },
              {
                "Name": "DissolveTextureTile_Y",
                "Association": "GlobalParameter",
                "Index": -1
              },
              {
                "Name": "|     Rotation Center ....",
                "Association": "GlobalParameter",
                "Index": -1
              },
              {
                "Name": "Atl_EmissiveHueShift",
                "Association": "GlobalParameter",
                "Index": -1
              },
              {
                "Name": "|     Normal Map Intensity",
                "Association": "GlobalParameter",
                "Index": -1
              },
              {
                "Name": "|     Specular Value     .",
                "Association": "GlobalParameter",
                "Index": -1
              },
              {
                "Name": "Speed X",
                "Association": "GlobalParameter",
                "Index": -1
              },
              {
                "Name": "|     BaseColor Map Tiling",
                "Association": "GlobalParameter",
                "Index": -1
              },
              {
                "Name": "UV Channel Tint",
                "Association": "GlobalParameter",
                "Index": -1
              },
              {
                "Name": "|     U Tiling ....",
                "Association": "GlobalParameter",
                "Index": -1
              },
              {
                "Name": "UV Tiling Master          .",
                "Association": "GlobalParameter",
                "Index": -1
              },
              {
                "Name": "|     BaseColor Map Intensity     .",
                "Association": "GlobalParameter",
                "Index": -1
              },
              {
                "Name": "Emissive_Tile_X",
                "Association": "GlobalParameter",
                "Index": -1
              },
              {
                "Name": "|     Rotation ....",
                "Association": "GlobalParameter",
                "Index": -1
              },
              {
                "Name": "BorderThresholdHigh",
                "Association": "GlobalParameter",
                "Index": -1
              },
              {
                "Name": "|     V Offset       .",
                "Association": "GlobalParameter",
                "Index": -1
              },
              {
                "Name": "|     V Tiling     .",
                "Association": "GlobalParameter",
                "Index": -1
              },
              {
                "Name": "|     Tint Map Intensity",
                "Association": "GlobalParameter",
                "Index": -1
              },
              {
                "Name": "|     U Offset",
                "Association": "GlobalParameter",
                "Index": -1
              },
              {
                "Name": "|     Rotation",
                "Association": "GlobalParameter",
                "Index": -1
              },
              {
                "Name": "|     Roughness Map Intensity",
                "Association": "GlobalParameter",
                "Index": -1
              },
              {
                "Name": "UV Channel          .",
                "Association": "GlobalParameter",
                "Index": -1
              },
              {
                "Name": "EmissiveTouchMultiplier",
                "Association": "GlobalParameter",
                "Index": -1
              },
              {
                "Name": "|     Rotation Center",
                "Association": "GlobalParameter",
                "Index": -1
              },
              {
                "Name": "|     Rotation          .",
                "Association": "GlobalParameter",
                "Index": -1
              },
              {
                "Name": "|     V Offset Tint",
                "Association": "GlobalParameter",
                "Index": -1
              },
              {
                "Name": "Atl_Specular",
                "Association": "GlobalParameter",
                "Index": -1
              },
              {
                "Name": "UV Channel ....",
                "Association": "GlobalParameter",
                "Index": -1
              },
              {
                "Name": "UltraLow_AO",
                "Association": "GlobalParameter",
                "Index": -1
              },
              {
                "Name": "Amount A",
                "Association": "GlobalParameter",
                "Index": -1
              },
              {
                "Name": "|     V Offset     .",
                "Association": "GlobalParameter",
                "Index": -1
              },
              {
                "Name": "DissolveProgress",
                "Association": "GlobalParameter",
                "Index": -1
              },
              {
                "Name": "|     Normal Map Intensity       .",
                "Association": "GlobalParameter",
                "Index": -1
              },
              {
                "Name": "StartLocation_WorldSpace",
                "Association": "GlobalParameter",
                "Index": -1
              },
              {
                "Name": "|     V Tiling",
                "Association": "GlobalParameter",
                "Index": -1
              },
              {
                "Name": "Dithering",
                "Association": "GlobalParameter",
                "Index": -1
              },
              {
                "Name": "|     V Tiling Tint",
                "Association": "GlobalParameter",
                "Index": -1
              },
              {
                "Name": "|     U Offset ....",
                "Association": "GlobalParameter",
                "Index": -1
              },
              {
                "Name": "GlowIntensity",
                "Association": "GlobalParameter",
                "Index": -1
              },
              {
                "Name": "|     Rotation     .",
                "Association": "GlobalParameter",
                "Index": -1
              },
              {
                "Name": "|     Overall Intensity",
                "Association": "GlobalParameter",
                "Index": -1
              },
              {
                "Name": "|     Tint Opacity Map Black Level",
                "Association": "GlobalParameter",
                "Index": -1
              },
              {
                "Name": "UltraLow_Metal",
                "Association": "GlobalParameter",
                "Index": -1
              },
              {
                "Name": "|     V Tiling          .",
                "Association": "GlobalParameter",
                "Index": -1
              },
              {
                "Name": "|     WS Height     .",
                "Association": "GlobalParameter",
                "Index": -1
              },
              {
                "Name": "|     Rotation       .",
                "Association": "GlobalParameter",
                "Index": -1
              },
              {
                "Name": "|     Normal Map Tiling",
                "Association": "GlobalParameter",
                "Index": -1
              },
              {
                "Name": "Custom Height Map Tiling",
                "Association": "GlobalParameter",
                "Index": -1
              },
              {
                "Name": "OpacityMaskOffset",
                "Association": "GlobalParameter",
                "Index": -1
              },
              {
                "Name": "Max A",
                "Association": "GlobalParameter",
                "Index": -1
              }
            ],
            "ExpressionGuids": [
              "F21C11984B680C0513605EBCC70F8DC9",
              "448734F2428F6EA238DD70BD9C5C4219",
              "0E1B85754FDD0433507D07BBA5ED34DE",
              "0B1943FB4099D828FFA13DB5D7573042",
              "B7075AB3418C0CD87401558EEBCE9583",
              "6A71022E473EC3EDE6D2C7B03D6188D4",
              "D690883C40AAEC95B4BEBBA472375BE6",
              "89FEB4DE47D24D0E34F72DA9125534F9",
              "E3727CCF4FDB929B3FAED9AA24A25333",
              "6B70398D46AED06BA9D62890E2F8D4D2",
              "DF115F734D5B96719182F6A7FC96E6D0",
              "39E8B8A146CB1553A77D0090C0219A68",
              "F272345F46643FAF98989193032F8B2E",
              "3E52A9F3452F90FBEEAD3B8961970E48",
              "C27F81054AC6DC8949D00AB49D1D85AD",
              "241A24D24883825E2970D88F31C0B0A2",
              "1EA891C24A65C4BB054BB0ABB476674F",
              "8843FEDD4642422B9740639FA39AC39F",
              "49070E504069ED6C5ED76EB80E336EC2",
              "862232BD4692ECE7CEF418B8EA0F24D6",
              "E0FB0DF54B9A914EA945348FEE0F03B6",
              "61B186E742002EC6680EF9BE6450BC42",
              "4990602E4BA45A0EDFE22FB4A0760FAC",
              "C49A3F7F4B46235609F0DBA7B985FB6E",
              "DF2951F04104EC1938CEC9843D99E4DA",
              "0C93EFD948852EA1C091E4838237AC2E",
              "AE55910D47A27707ED40018F152B2E93",
              "4F931FCE4E0266D3F8B0F4AF3BA47E9A",
              "71BBB4634514B3FBECBD43B46F3E8A84",
              "E7ABC39A499282CA12AF3582C50C8F96",
              "E9283AB3450019C4DBBE91A6BA87A3D5",
              "80FC32A742BD10D4B41BC388642A9A3F",
              "E00E2C4949C103138EFD429E8DDED0FD",
              "EB8F00DC4934DA1063C60A8A26182AD9",
              "AB80C77A494AFE26794BCA8C12BC4866",
              "0D3F6D9140B14751B7B4B8B9A8F205E2",
              "5A193DB84AA589666AEAA0A734E2E9E2",
              "2E5B9B3D436EB85AC024FB968BC8231E",
              "C17AB2054D22FC487793568F39D4BEB8",
              "E04635F84232B05EB4FDF8A567363EBB",
              "A0F5B32B4DEFB4A2F3FA1BB35A4E4C2D",
              "ACB96AB342DCAFD4056AB792442B5E71",
              "CD1B625F47B1BB6EACBE9E9F84E1E72D",
              "FDF3F69449F41F773EDC4F9681DA6EA6",
              "3B322E2B48BC147B003782A57E0119F7",
              "B989E43444E5FE6631E5A38125087E90",
              "94E01B354892E969116C7998D3AA95E3",
              "C9CC660E4799BD1C17F0CAA9028B11AD",
              "703F62AC4C7AD8FE540DB08CE5C7CA09",
              "0C8DAFC244DBE478E6A5CEA224626CAA",
              "CDC0E44B4CDB5891E5B1F4907F423D65",
              "833267BE444C61FFA5500A81AD3887DB",
              "2E8C9D114841D4B4957431B74C4F8413",
              "59F4540044AD73005B774FBA14B85865",
              "506F77764FBCDF41EE85038DAA83EF94",
              "D2B45A85481E2E8A8281E29F606EEB52",
              "78D82EBA413415FE5BF1B1905D5385A5",
              "C5B29B824B46A09F77C14B8D9E1ADD6F",
              "A2A4AC714BED58C02E5F1B827FD3BACA",
              "BB6ADCD847114B1F9FCC28988772124D",
              "80B515A348E1782C453A638F8120B953",
              "00CDEB57446C4175F2B89C84EF95A378",
              "778AECD94E97652F5841259AC61F04C3",
              "01D38689455F920D777C5089A1061D76",
              "E04635F84232B05EB4FDF8A567363EBB",
              "2EADA664469CFB100D61698799163F1F",
              "6DB784EB41CF82D85EC3F0A24ECB9BA9",
              "F001622D40ECC9EDCC64E4816B40F9AF",
              "44F334F64F5C524970C60B83BB8E6F56",
              "74D90E9345D0CE5A7022A1A1E99C1284",
              "79B53A0B4D1D6C0C906C7486450BBAAB",
              "EE07AFFD41742AFAEE2817AF547C9652",
              "806FF4BD49C4D346F29610A0BD708901",
              "29C8BC6044CA2FFD382706908705B4BF",
              "12AFB13D4714D6F4D7E71E99C023F02E",
              "DF2951F04104EC1938CEC9843D99E4DA",
              "FF164B29405075820079CBAC6C3B258A",
              "0F58EA37405E90E5D4BCBF9E5AA7F1E4",
              "0127D5E248688C918F7A3D963E12AC62",
              "B10CEB0D485EE49DCB8FA79CD864C3ED",
              "C81F3DC7429DF6E0DCE9AE9CF0E0F54B",
              "CAC204B3440A6798503B37936509BA04",
              "856B88964B0BDA49E3456FB8CE118D13",
              "48BB48A7430546E51FE76AB5E169CC8E",
              "D296294B4712C299AFBE669658F99FDB",
              "1996430244F9F87EC4C5FC87FB6B662C",
              "EB70DBA94C151C1856A7249DDC7DA94A",
              "8083E7864567BFD15B57EF93D8A50C12",
              "E5BFAC134F8AD906B0CA8CA183F8FC64",
              "08E45077495239CFA5650FAB90905C77",
              "17CB2CD84228480380B168B2F3C65820",
              "48433B4F4948FAF01FC65FACE0C27978",
              "EBFAAA79467B8D975843979B5794970D",
              "DF115F734D5B96719182F6A7FC96E6D0",
              "D405FA9D4D9B18BC089D089B08C56892",
              "B1BB507E4DD1EBD8C055899F9192F25C",
              "BEBEC76A4DD54FDC0664DBAE5E81D3CE",
              "19E7582E4E323D333A9648AEA7C213B0",
              "328DA3AB4F03077B0F2D089B488CDE27",
              "1BE3A4064CA64E663BA9ACA77D813682",
              "3B322E2B48BC147B003782A57E0119F7",
              "B10CEB0D485EE49DCB8FA79CD864C3ED",
              "8080F5B3440D498656CE319EA5782CE1",
              "ED4AE3C3495CFD289E8C4A9A9E993DE9",
              "F26CDCF94A595F8BD6DA9BAE71A57C9C",
              "45AF465B42E83E79D3A7D5BD30EF955E",
              "B7309C3C4B85D00BE4CEE697CF4229B9",
              "1C4D00D141E8C4F3093403ADF6E64D22",
              "6BB65F4647F08EDE9D4DD3BE903D20C7",
              "1CD9C0FE47D022D3A8669E9E005AF436",
              "DE141BEA47E4DAD4676F258CBE79360D",
              "B0C5C4D448EFDCD9D1835D9F7691ABDA",
              "A8A5862041A0CD42757682A7A9448832",
              "F4E663864A0965181BE5E28720308BA3",
              "31CD878D4201738D293FE6902D1D6679",
              "F26CDCF94A595F8BD6DA9BAE71A57C9C",
              "A30A7CF94A3C6257A1EEB2AA39B5BD8B",
              "3A7DFA66472D77E65A43CDB454A12E3E",
              "A8A5862041A0CD42757682A7A9448832",
              "E8A2848F49C247EEF0A7F49707693896",
              "5B139CCB48AF37D4C25EDF89CC0BAE82",
              "A7F99C78453A5AD1FD2F92AFF195BF00",
              "9A9D8BE04F03EED486217A8AE1DD04A5",
              "87839D4A4A6F3B9B62D559B4A2A761A4",
              "074542C94C5740C2843EF697C7F4460C",
              "007BBBE1446239B5BC350CAB4F786A0C",
              "98A7F5264A5799F012069DAF366F481A",
              "9969685C47F16542E998379B6AA0F80D",
              "EE07AFFD41742AFAEE2817AF547C9652",
              "E3130DDA495F93196C7B5F84B4177F4C",
              "8114DE3D451958E0721A05A5F6B45009",
              "B9EBDAEE4D994124193ACD9A14BBD67C",
              "E5679C9A43EC50C2415A39886A14E9AE",
              "DE486B354F6D27B8FEDC5481FA7B3907",
              "2E8C9D114841D4B4957431B74C4F8413",
              "E5EB78074CB975C9B52F97A1057D8D45",
              "3798444D47FF68BAB76D378760DAFE3A",
              "B13189254F3ED1175081749EB781F09F",
              "C7B2882E4A06808471FBB7A9EECBE407",
              "63155A3E4E898E97CB89A5A599C25949",
              "E44BF9374DBC5E49BB7B4A8DF5FB1477"
            ],
            "Overrides": [
              false,
              false,
              false,
              false,
              false,
              false,
              false,
              false,
              false,
              false,
              false,
              false,
              false,
              false,
              false,
              false,
              false,
              false,
              false,
              false,
              false,
              false,
              false,
              false,
              false,
              false,
              false,
              false,
              false,
              false,
              false,
              false,
              false,
              false,
              false,
              false,
              false,
              false,
              false,
              false,
              false,
              false,
              false,
              false,
              false,
              false,
              false,
              false,
              false,
              false,
              false,
              false,
              false,
              false,
              false,
              false,
              false,
              false,
              false,
              false,
              false,
              false,
              false,
              false,
              false,
              false,
              false,
              false,
              false,
              false,
              false,
              false,
              false,
              false,
              false,
              false,
              false,
              false,
              false,
              false,
              false,
              false,
              false,
              false,
              false,
              false,
              false,
              false,
              false,
              false,
              false,
              false,
              false,
              false,
              false,
              false,
              false,
              false,
              false,
              false,
              false,
              false,
              false,
              false,
              false,
              false,
              false,
              false,
              false,
              false,
              false,
              false,
              false,
              false,
              false,
              false,
              false,
              false,
              false,
              false,
              false,
              false,
              false,
              false,
              false,
              false,
              false,
              false,
              false,
              false,
              false,
              false,
              false,
              false,
              false,
              false,
              false,
              false,
              false,
              false,
              false
            ]
          },
          "Entries_NK01": {
            "NameHashes": [
              3374365783382202529,
              4359794668474716310,
              6180953405497102022,
              7141051148651797661,
              7949039858076611550,
              8622795175588219902,
              13273100671322145683,
              14403008326147554990,
              15328627375946152563,
              16014420144181682489,
              16477445497430518460
            ],
            "ParameterInfos": [
              {
                "Name": "Texture Size",
                "Association": "GlobalParameter",
                "Index": -1
              },
              {
                "Name": "VeinsColor",
                "Association": "GlobalParameter",
                "Index": -1
              },
              {
                "Name": "ColorTint_Fade",
                "Association": "GlobalParameter",
                "Index": -1
              },
              {
                "Name": "Main_EmissiveValue",
                "Association": "GlobalParameter",
                "Index": -1
              },
              {
                "Name": "Emissive Color ....",
                "Association": "GlobalParameter",
                "Index": -1
              },
              {
                "Name": "BaseColor     .",
                "Association": "GlobalParameter",
                "Index": -1
              },
              {
                "Name": "|     Tint Color",
                "Association": "GlobalParameter",
                "Index": -1
              },
              {
                "Name": "Texture Mask Size",
                "Association": "GlobalParameter",
                "Index": -1
              },
              {
                "Name": "EmissiveTouch",
                "Association": "GlobalParameter",
                "Index": -1
              },
              {
                "Name": "BaseColor",
                "Association": "GlobalParameter",
                "Index": -1
              },
              {
                "Name": "BorderColor",
                "Association": "GlobalParameter",
                "Index": -1
              }
            ],
            "ExpressionGuids": [
              "C27EC0EF4FB61A480968A098CF2414B5",
              "8947B65F475ECA964293149BC9A54C63",
              "C432B99C469D933C927B5E9BC5681EF5",
              "4C6BE4434D89161CEC660F88AD129330",
              "A2B035FC462B57C62766BEA52EAD667F",
              "E0C8AE73455F22862E38758F10E80ABC",
              "844A924949ECD570BEAC00B5AF5938DC",
              "2AA56393410A3156A27D9A90506941B0",
              "6BCFFD864D904FEC7B391CAAE2A2C75D",
              "10E5873044406FAD470924BA5101E523",
              "23DFC9D74E434C071BBF60B401917558"
            ],
            "Overrides": [
              false,
              false,
              false,
              false,
              false,
              false,
              false,
              false,
              false,
              false,
              false
            ]
          },
          "Entries_NK02": {
            "NameHashes": [
              511768318761210393,
              1743377833861675513,
              1762214970934643857,
              1921719964488834965,
              2445002505845564225,
              2794072116701829743,
              3053973466342505654,
              3136819919207692239,
              4093712129551234549,
              4241579619957069033,
              4268444660294807373,
              5571971884130996025,
              5969446413979139084,
              5976353017368017520,
              8938744695559993442,
              10151050335279642284,
              10867552505175725580,
              11157098469543728180,
              11232898073730699072,
              11650036334739555983,
              12076515603125919684,
              13000102593149591936,
              14373069959842431199,
              14674130376188065132,
              15681864496249902260,
              16278355857170508878,
              16443232358051847721
            ],
            "ParameterInfos": [
              {
                "Name": "HRM\\ORM Map     .",
                "Association": "GlobalParameter",
                "Index": -1
              },
              {
                "Name": "AORoughnessMetallic A",
                "Association": "GlobalParameter",
                "Index": -1
              },
              {
                "Name": "Normal Map       .",
                "Association": "GlobalParameter",
                "Index": -1
              },
              {
                "Name": "Opacity Map ....",
                "Association": "GlobalParameter",
                "Index": -1
              },
              {
                "Name": "DissolveRamps",
                "Association": "GlobalParameter",
                "Index": -1
              },
              {
                "Name": "Opacity Map          .",
                "Association": "GlobalParameter",
                "Index": -1
              },
              {
                "Name": "BaseColor Map     .",
                "Association": "GlobalParameter",
                "Index": -1
              },
              {
                "Name": "|     BaseColor Tint Map",
                "Association": "GlobalParameter",
                "Index": -1
              },
              {
                "Name": "Diffuse",
                "Association": "GlobalParameter",
                "Index": -1
              },
              {
                "Name": "BaseColor Map",
                "Association": "GlobalParameter",
                "Index": -1
              },
              {
                "Name": "Normal Map     .",
                "Association": "GlobalParameter",
                "Index": -1
              },
              {
                "Name": "Normal A",
                "Association": "GlobalParameter",
                "Index": -1
              },
              {
                "Name": "Specular Map",
                "Association": "GlobalParameter",
                "Index": -1
              },
              {
                "Name": "Normal Map Detail",
                "Association": "GlobalParameter",
                "Index": -1
              },
              {
                "Name": "Roughness Map Detail",
                "Association": "GlobalParameter",
                "Index": -1
              },
              {
                "Name": "Emissive Map ....",
                "Association": "GlobalParameter",
                "Index": -1
              },
              {
                "Name": "AORoughnessMetallic",
                "Association": "GlobalParameter",
                "Index": -1
              },
              {
                "Name": "Main_EmissiveMask",
                "Association": "GlobalParameter",
                "Index": -1
              },
              {
                "Name": "Main_BaseColor",
                "Association": "GlobalParameter",
                "Index": -1
              },
              {
                "Name": "Custom HeightMap",
                "Association": "GlobalParameter",
                "Index": -1
              },
              {
                "Name": "Normal Map",
                "Association": "GlobalParameter",
                "Index": -1
              },
              {
                "Name": "|     Tint Opacity Map",
                "Association": "GlobalParameter",
                "Index": -1
              },
              {
                "Name": "Diffuse A",
                "Association": "GlobalParameter",
                "Index": -1
              },
              {
                "Name": "HRM\\ORM Map",
                "Association": "GlobalParameter",
                "Index": -1
              },
              {
                "Name": "FlowMap Emissive",
                "Association": "GlobalParameter",
                "Index": -1
              },
              {
                "Name": "Blood Dirt Emissive",
                "Association": "GlobalParameter",
                "Index": -1
              },
              {
                "Name": "DissolveTexture",
                "Association": "GlobalParameter",
                "Index": -1
              }
            ],
            "ExpressionGuids": [
              "55D415FD4D0A7C895945DD913E1B9502",
              "BDA81EBD431DA42C453248BA09F329EB",
              "27C687BF42A1BCF48866C1A951929514",
              "5EF05E484D99736F5A437EACFA63C20A",
              "97B508424AC74C8A261A789DF9EAB6BD",
              "5EF05E484D99736F5A437EACFA63C20A",
              "E94DED414184566AE1C7199F6E9BF23E",
              "1EA58F274181723AD78A358D40396F27",
              "EF162D714DF7AF5DC54B468008358610",
              "9217CC0343B500A41C95A69BCF0B8993",
              "402432EB452BE290D5196695F2CE5891",
              "B32094814BCBAE2F4DDC858F1D4B3157",
              "05BD114A413172E7147643AD68100A45",
              "383233D649F12777C3CAFD838033996D",
              "7C4005124DC880CE484DB89C172DFD08",
              "C1E73E04433D3844A14750A990CB1F79",
              "2D19C0DA44B019280B9D6F82533725C1",
              "4234AB134D8E3582523E8BA774591E83",
              "F11FDC05488F18CD8A48FD8A11D690B1",
              "1AACF93643B9C43C0AD6AD9E70EFB256",
              "8E4D9DB24FE26D11FD4E79AD2C0B2630",
              "A0B03B234156A45B1AE5EA936BAFF3DC",
              "6ACD3FE94F401D8E61C8A19AD3775413",
              "C9CF50814FC975CC284BC5B84D4E5029",
              "52B780B14E3DEB60F415D5ACD09D1D72",
              "17D055BB48F09EC7F0EF28A82FAE59BF",
              "737F6C864452DC74BB02B98D63A6C979"
            ],
            "Overrides": [
              false,
              false,
              false,
              false,
              false,
              false,
              false,
              false,
              false,
              false,
              false,
              false,
              false,
              false,
              false,
              false,
              false,
              false,
              false,
              false,
              false,
              false,
              false,
              false,
              false,
              false,
              false
            ]
          },
          "ScalarValues": [
            1.0,
            1.0,
            1.0,
            0.5,
            1.0,
            10.0,
            0.0,
            1.0,
            0.0,
            200.0,
            0.0,
            1.0,
            1.0,
            0.0,
            2.0,
            2.0,
            1.0,
            1.0,
            0.5,
            1.0,
            40.0,
            1.0,
            1.0,
            1.0,
            0.0,
            1.0,
            1.0,
            0.0,
            1.0,
            1.5,
            1.0,
            0.0,
            1.0,
            4000.0,
            1.0,
            0.5,
            350.0,
            22.0,
            1.0,
            0.5,
            0.0,
            0.0,
            1.0,
            1.0,
            1.0,
            0.1,
            1.0,
            0.0,
            5.0,
            0.0,
            0.0,
            1.0,
            1.0,
            3.0,
            1.0,
            0.0,
            0.0,
            0.5,
            0.0,
            1.0,
            0.0,
            3.0,
            1.0,
            0.0,
            0.5,
            0.0,
            0.0,
            0.0,
            1.0,
            1.0,
            1.0,
            0.0,
            0.0,
            400.0,
            0.0,
            0.0,
            1.0,
            10.0,
            1.0,
            1.0,
            1.0,
            1.0,
            1.0,
            -25.0,
            0.0,
            1.0,
            0.0,
            1.0,
            0.0,
            1.0,
            0.3,
            1.0,
            3.0,
            0.0,
            0.0,
            1.0,
            0.5,
            0.0,
            1.0,
            0.0,
            1.0,
            1.0,
            1.0,
            1.0,
            0.0,
            0.015,
            0.0,
            1.0,
            1.0,
            0.0,
            0.0,
            1.0,
            0.0,
            1.0,
            0.0,
            0.0,
            0.0,
            0.0,
            0.0,
            1.0,
            0.0,
            0.0,
            1.0,
            1.0,
            0.0,
            1.0,
            1.0,
            1.0,
            0.0,
            750.0,
            0.0,
            0.0,
            1.0,
            0.0,
            1.0,
            1.0,
            0.0,
            1.0,
            1.0,
            2.5,
            1.0
          ],
          "VectorValues": [
            {
              "R": 150.0,
              "G": 150.0,
              "B": 150.0,
              "A": 0.0,
              "Hex": "6A6A6A"
            },
            {
              "R": 0.1,
              "G": 0.017777,
              "B": 0.0075,
              "A": 1.0,
              "Hex": "1A0502"
            },
            {
              "R": 1.0,
              "G": 1.0,
              "B": 1.0,
              "A": 1.0,
              "Hex": "FFFFFF"
            },
            {
              "R": 0.0,
              "G": 0.0,
              "B": 0.0,
              "A": 0.0,
              "Hex": "000000"
            },
            {
              "R": 1.0,
              "G": 0.821232,
              "B": 0.0,
              "A": 0.0,
              "Hex": "FFD100"
            },
            {
              "R": 0.212088,
              "G": 0.0,
              "B": 0.927083,
              "A": 1.0,
              "Hex": "3600EC"
            },
            {
              "R": 0.0,
              "G": 1.0,
              "B": 0.950892,
              "A": 1.0,
              "Hex": "00FFF2"
            },
            {
              "R": 500.0,
              "G": 500.0,
              "B": 500.0,
              "A": 0.0,
              "Hex": "0C0C0C"
            },
            {
              "R": 0.0,
              "G": 0.0,
              "B": 0.0,
              "A": 0.0,
              "Hex": "000000"
            },
            {
              "R": 0.856177,
              "G": 0.0,
              "B": 1.0,
              "A": 1.0,
              "Hex": "DA00FF"
            },
            {
              "R": 5.0,
              "G": 2.250738,
              "B": 1.09375,
              "A": 1.0,
              "Hex": "FB3E17"
            }
          ],
          "TextureValues": [
            {
              "ObjectName": "T_MRH_Default",
              "OuterIndex": {
                "ObjectName": "/Game/Textures/Environment/_Common/Defaults/T_MRH_Default",
                "OuterIndex": 0
              }
            },
            {
              "ObjectName": "T_Vomit01_ORM",
              "OuterIndex": {
                "ObjectName": "/Game/Characters/Campers/Textures/Vomit/T_Vomit01_ORM",
                "OuterIndex": 0
              }
            },
            {
              "ObjectName": "T_NormalMap_Default",
              "OuterIndex": {
                "ObjectName": "/Game/Textures/Environment/_Common/Defaults/T_NormalMap_Default",
                "OuterIndex": 0
              }
            },
            {
              "ObjectName": "T_RgbMaskWithAlpha_Default",
              "OuterIndex": {
                "ObjectName": "/Game/Textures/Environment/_Common/Defaults/T_RgbMaskWithAlpha_Default",
                "OuterIndex": 0
              }
            },
            {
              "ObjectName": "T_FX_DissolveRamp",
              "OuterIndex": {
                "ObjectName": "/Game/Effects/Textures/T_FX_DissolveRamp",
                "OuterIndex": 0
              }
            },
            {
              "ObjectName": "T_RgbMaskWithAlpha_Default",
              "OuterIndex": {
                "ObjectName": "/Game/Textures/Environment/_Common/Defaults/T_RgbMaskWithAlpha_Default",
                "OuterIndex": 0
              }
            },
            {
              "ObjectName": "T_Diffuse_Default",
              "OuterIndex": {
                "ObjectName": "/Game/Textures/Environment/_Common/Defaults/T_Diffuse_Default",
                "OuterIndex": 0
              }
            },
            {
              "ObjectName": "T_RgbMaskWithAlpha_Default",
              "OuterIndex": {
                "ObjectName": "/Game/Textures/Environment/_Common/Defaults/T_RgbMaskWithAlpha_Default",
                "OuterIndex": 0
              }
            },
            {
              "ObjectName": "Black",
              "OuterIndex": {
                "ObjectName": "/Game/Textures/Environment/Tiles/Black",
                "OuterIndex": 0
              }
            },
            {
              "ObjectName": "T_DiffuseWithAlpha_Default",
              "OuterIndex": {
                "ObjectName": "/Game/Textures/Environment/_Common/Defaults/T_DiffuseWithAlpha_Default",
                "OuterIndex": 0
              }
            },
            {
              "ObjectName": "T_NormalMap_Default",
              "OuterIndex": {
                "ObjectName": "/Game/Textures/Environment/_Common/Defaults/T_NormalMap_Default",
                "OuterIndex": 0
              }
            },
            {
              "ObjectName": "T_Vomit01_N",
              "OuterIndex": {
                "ObjectName": "/Game/Characters/Campers/Textures/Vomit/T_Vomit01_N",
                "OuterIndex": 0
              }
            },
            {
              "ObjectName": "T_Specular_Default",
              "OuterIndex": {
                "ObjectName": "/Game/Textures/Environment/_Common/Defaults/T_Specular_Default",
                "OuterIndex": 0
              }
            },
            {
              "ObjectName": "T_NormalMap_Default",
              "OuterIndex": {
                "ObjectName": "/Game/Textures/Environment/_Common/Defaults/T_NormalMap_Default",
                "OuterIndex": 0
              }
            },
            {
              "ObjectName": "T_RgbMask_Default",
              "OuterIndex": {
                "ObjectName": "/Game/Textures/Environment/_Common/Defaults/T_RgbMask_Default",
                "OuterIndex": 0
              }
            },
            {
              "ObjectName": "T_RgbMaskWithAlpha_Default",
              "OuterIndex": {
                "ObjectName": "/Game/Textures/Environment/_Common/Defaults/T_RgbMaskWithAlpha_Default",
                "OuterIndex": 0
              }
            },
            {
              "ObjectName": "Yellow_Linear",
              "OuterIndex": {
                "ObjectName": "/Game/Textures/Environment/Tiles/Yellow_Linear",
                "OuterIndex": 0
              }
            },
            {
              "ObjectName": "White_Linear",
              "OuterIndex": {
                "ObjectName": "/Game/Textures/Environment/Tiles/White_Linear",
                "OuterIndex": 0
              }
            },
            {
              "ObjectName": "T_checker_grid",
              "OuterIndex": {
                "ObjectName": "/Game/Textures/Props/Misc/T_checker_grid",
                "OuterIndex": 0
              }
            },
            {
              "ObjectName": "T_MRH_Default",
              "OuterIndex": {
                "ObjectName": "/Game/Textures/Environment/_Common/Defaults/T_MRH_Default",
                "OuterIndex": 0
              }
            },
            {
              "ObjectName": "T_NormalMap_Default",
              "OuterIndex": {
                "ObjectName": "/Game/Textures/Environment/_Common/Defaults/T_NormalMap_Default",
                "OuterIndex": 0
              }
            },
            {
              "ObjectName": "T_RgbMaskWithAlpha_Default",
              "OuterIndex": {
                "ObjectName": "/Game/Textures/Environment/_Common/Defaults/T_RgbMaskWithAlpha_Default",
                "OuterIndex": 0
              }
            },
            {
              "ObjectName": "T_Vomit01_BC",
              "OuterIndex": {
                "ObjectName": "/Game/Characters/Campers/Textures/Vomit/T_Vomit01_BC",
                "OuterIndex": 0
              }
            },
            {
              "ObjectName": "T_MRH_Default",
              "OuterIndex": {
                "ObjectName": "/Game/Textures/Environment/_Common/Defaults/T_MRH_Default",
                "OuterIndex": 0
              }
            },
            {
              "ObjectName": "T_Clouds_01",
              "OuterIndex": {
                "ObjectName": "/Game/Effects/Textures/T_Clouds_01",
                "OuterIndex": 0
              }
            },
            {
              "ObjectName": "T_SmokeTile",
              "OuterIndex": {
                "ObjectName": "/Game/Effects/Textures/T_SmokeTile",
                "OuterIndex": 0
              }
            },
            {
              "ObjectName": "T_DissolveTextures",
              "OuterIndex": {
                "ObjectName": "/Game/Effects/Textures/T_DissolveTextures",
                "OuterIndex": 0
              }
            }
          ]
        },
        "ReferencedTextures": [
          {
            "ObjectName": "T_Diffuse_Default",
            "OuterIndex": {
              "ObjectName": "/Game/Textures/Environment/_Common/Defaults/T_Diffuse_Default",
              "OuterIndex": 0
            }
          },
          {
            "ObjectName": "T_NormalMap_Default",
            "OuterIndex": {
              "ObjectName": "/Game/Textures/Environment/_Common/Defaults/T_NormalMap_Default",
              "OuterIndex": 0
            }
          },
          {
            "ObjectName": "T_MRH_Default",
            "OuterIndex": {
              "ObjectName": "/Game/Textures/Environment/_Common/Defaults/T_MRH_Default",
              "OuterIndex": 0
            }
          },
          {
            "ObjectName": "BlendFunc_DefBlend",
            "OuterIndex": {
              "ObjectName": "/Engine/EngineMaterials/BlendFunc_DefBlend",
              "OuterIndex": 0
            }
          },
          {
            "ObjectName": "BlendFunc_DefBase",
            "OuterIndex": {
              "ObjectName": "/Engine/EngineMaterials/BlendFunc_DefBase",
              "OuterIndex": 0
            }
          },
          {
            "ObjectName": "T_DiffuseWithAlpha_Default",
            "OuterIndex": {
              "ObjectName": "/Game/Textures/Environment/_Common/Defaults/T_DiffuseWithAlpha_Default",
              "OuterIndex": 0
            }
          },
          {
            "ObjectName": "T_Specular_Default",
            "OuterIndex": {
              "ObjectName": "/Game/Textures/Environment/_Common/Defaults/T_Specular_Default",
              "OuterIndex": 0
            }
          },
          {
            "ObjectName": "T_RgbMask_Default",
            "OuterIndex": {
              "ObjectName": "/Game/Textures/Environment/_Common/Defaults/T_RgbMask_Default",
              "OuterIndex": 0
            }
          },
          {
            "ObjectName": "T_RgbMaskWithAlpha_Default",
            "OuterIndex": {
              "ObjectName": "/Game/Textures/Environment/_Common/Defaults/T_RgbMaskWithAlpha_Default",
              "OuterIndex": 0
            }
          },
          0,
          {
            "ObjectName": "DefaultDiffuse",
            "OuterIndex": {
              "ObjectName": "/Engine/EngineMaterials/DefaultDiffuse",
              "OuterIndex": 0
            }
          },
          {
            "ObjectName": "T_SmokeTile",
            "OuterIndex": {
              "ObjectName": "/Game/Effects/Textures/T_SmokeTile",
              "OuterIndex": 0
            }
          },
          {
            "ObjectName": "T_Vomit01_BC",
            "OuterIndex": {
              "ObjectName": "/Game/Characters/Campers/Textures/Vomit/T_Vomit01_BC",
              "OuterIndex": 0
            }
          },
          {
            "ObjectName": "Black",
            "OuterIndex": {
              "ObjectName": "/Game/Textures/Environment/Tiles/Black",
              "OuterIndex": 0
            }
          },
          {
            "ObjectName": "T_Vomit01_ORM",
            "OuterIndex": {
              "ObjectName": "/Game/Characters/Campers/Textures/Vomit/T_Vomit01_ORM",
              "OuterIndex": 0
            }
          },
          {
            "ObjectName": "Yellow_Linear",
            "OuterIndex": {
              "ObjectName": "/Game/Textures/Environment/Tiles/Yellow_Linear",
              "OuterIndex": 0
            }
          },
          {
            "ObjectName": "T_Vomit01_N",
            "OuterIndex": {
              "ObjectName": "/Game/Characters/Campers/Textures/Vomit/T_Vomit01_N",
              "OuterIndex": 0
            }
          },
          {
            "ObjectName": "T_DissolveTextures",
            "OuterIndex": {
              "ObjectName": "/Game/Effects/Textures/T_DissolveTextures",
              "OuterIndex": 0
            }
          },
          {
            "ObjectName": "T_FX_DissolveRamp",
            "OuterIndex": {
              "ObjectName": "/Game/Effects/Textures/T_FX_DissolveRamp",
              "OuterIndex": 0
            }
          },
          {
            "ObjectName": "T_Clouds_01",
            "OuterIndex": {
              "ObjectName": "/Game/Effects/Textures/T_Clouds_01",
              "OuterIndex": 0
            }
          },
          {
            "ObjectName": "White_Linear",
            "OuterIndex": {
              "ObjectName": "/Game/Textures/Environment/Tiles/White_Linear",
              "OuterIndex": 0
            }
          },
          {
            "ObjectName": "T_checker_grid",
            "OuterIndex": {
              "ObjectName": "/Game/Textures/Props/Misc/T_checker_grid",
              "OuterIndex": 0
            }
          },
          {
            "ObjectName": "Good64x64TilingNoiseHighFreq",
            "OuterIndex": {
              "ObjectName": "/Engine/EngineMaterials/Good64x64TilingNoiseHighFreq",
              "OuterIndex": 0
            }
          }
        ],
        "FunctionInfos": [
          {
            "StateId": "144CAA0F4D28F307379D4CAE4267246D",
            "Function": {
              "ObjectName": "MF_Atlanta_Filter_v2_Default",
              "OuterIndex": {
                "ObjectName": "/Game/Materials/MaterialFunctions/Atlanta/MF_Atlanta_Filter_v2_Default",
                "OuterIndex": 0
              }
            }
          },
          {
            "StateId": "A9BF2F14427DC5DEF27BC390780E317C",
            "Function": {
              "ObjectName": "MF_QualityAndFeatureSwitches",
              "OuterIndex": {
                "ObjectName": "/Game/Materials/MaterialFunctions/Environment/MF_QualityAndFeatureSwitches",
                "OuterIndex": 0
              }
            }
          },
          {
            "StateId": "175BF3B54513BA51CA9B3A98A72EA630",
            "Function": {
              "ObjectName": "MF_WS_Overlay",
              "OuterIndex": {
                "ObjectName": "/Game/Materials/MaterialFunctions/Environment/MF_WS_Overlay",
                "OuterIndex": 0
              }
            }
          },
          {
            "StateId": "CD42252F42DB3A2A3253DC900AA94937",
            "Function": {
              "ObjectName": "MF_Material",
              "OuterIndex": {
                "ObjectName": "/Game/Materials/MaterialFunctions/Environment/MF_Material",
                "OuterIndex": 0
              }
            }
          },
          {
            "StateId": "DE171AC4466BB060B606B682FB246F6E",
            "Function": {
              "ObjectName": "MF_018_FadeRadius",
              "OuterIndex": {
                "ObjectName": "/Game/Materials/MaterialFunctions/MF_018_FadeRadius",
                "OuterIndex": 0
              }
            }
          },
          {
            "StateId": "CB8862EF41AE3088BDA78FAEECAAE64C",
            "Function": {
              "ObjectName": "MF_NM_Overlay",
              "OuterIndex": {
                "ObjectName": "/Game/Materials/MaterialFunctions/Environment/MF_NM_Overlay",
                "OuterIndex": 0
              }
            }
          },
          {
            "StateId": "D70D850543410FF3B38425B84810B1FA",
            "Function": {
              "ObjectName": "MFN_Object_OverlayTexture",
              "OuterIndex": {
                "ObjectName": "/Game/Materials/MaterialFunctions/MFN_Object_OverlayTexture",
                "OuterIndex": 0
              }
            }
          },
          {
            "StateId": "A149C7484CEFF468288D7BA4FD69D590",
            "Function": {
              "ObjectName": "MFN_Char_Dissolve",
              "OuterIndex": {
                "ObjectName": "/Game/Effects/Materials/Functions/Dissolve/MFN_Char_Dissolve",
                "OuterIndex": 0
              }
            }
          },
          {
            "StateId": "1CE7E72B41E6F8998ED2EB993D551FAC",
            "Function": {
              "ObjectName": "MFN_PanningEmissive",
              "OuterIndex": {
                "ObjectName": "/Game/Materials/MaterialFunctions/Atlanta/MFN_PanningEmissive",
                "OuterIndex": 0
              }
            }
          },
          {
            "StateId": "EDEC54B841511C177C858FB9D5829C12",
            "Function": {
              "ObjectName": "MF_Masked",
              "OuterIndex": {
                "ObjectName": "/Game/Materials/MaterialFunctions/Environment/MF_Masked",
                "OuterIndex": 0
              }
            }
          },
          {
            "StateId": "AF4890EB4C5F920ADA6F40997889C65E",
            "Function": {
              "ObjectName": "MF_Material_1_Emissive",
              "OuterIndex": {
                "ObjectName": "/Game/Materials/MaterialFunctions/Environment/MF_Material_1_Emissive",
                "OuterIndex": 0
              }
            }
          }
        ],
        "ParameterCollectionInfos": [
          {
            "StateId": "CEF552974C29480110968BB6495550A1",
            "ParameterCollection": {
              "ObjectName": "MPC_Atlanta_Fade",
              "OuterIndex": {
                "ObjectName": "/Game/Materials/MaterialFunctions/Atlanta/MPC_Atlanta_Fade",
                "OuterIndex": 0
              }
            }
          }
        ],
        "QualityLevelsUsed": [
          true,
          true,
          false
        ]
      },
      "TextureStreamingData": [
        {
          "SamplingScale": 1.0,
          "UVChannelIndex": 2,
          "TextureName": "T_MRH_Default"
        }
      ]
    }
  }
]