[
  {
    "Type": "BlueprintGeneratedClass",
    "Name": "BP_Brl_RoofRays01_C",
    "Properties": {
      "SimpleConstructionScript": {
        "ObjectName": "SimpleConstructionScript BP_Brl_RoofRays01_C:SimpleConstructionScript_4",
        "ObjectPath": "DeadByDaylight/Content/Blueprints/Props/08-Boreal/BP_BRL_RoofRays01.7"
      }
    },
    "SuperStruct": {
      "ObjectName": "Class Actor",
      "ObjectPath": "/Script/Engine"
    },
    "ChildProperties": [
      {
        "Type": "ObjectProperty",
        "Name": "LightConeNormal",
        "Flags": 2097153,
        "ElementSize": 8,
        "PropertyFlags": 17180393476,
        "PropertyClass": {
          "ObjectName": "Class StaticMeshComponent",
          "ObjectPath": "/Script/Engine"
        }
      },
      {
        "Type": "ObjectProperty",
        "Name": "Scene",
        "Flags": 2097153,
        "ElementSize": 8,
        "PropertyFlags": 17180393476,
        "PropertyClass": {
          "ObjectName": "Class SceneComponent",
          "ObjectPath": "/Script/Engine"
        }
      }
    ],
    "ClassFlags": 8652820,
    "ClassWithin": {
      "ObjectName": "Class Object",
      "ObjectPath": "/Script/CoreUObject"
    },
    "ClassConfigName": "Engine",
    "bCooked": true,
    "ClassDefaultObject": {
      "ObjectName": "BP_Brl_RoofRays01_C Default__BP_Brl_RoofRays01_C",
      "ObjectPath": "DeadByDaylight/Content/Blueprints/Props/08-Boreal/BP_BRL_RoofRays01.1"
    }
  },
  {
    "Type": "BP_Brl_RoofRays01_C",
    "Name": "Default__BP_Brl_RoofRays01_C",
    "Properties": {
      "PrimaryActorTick": {
        "bStartWithTickEnabled": false
      }
    }
  },
  {
    "Type": "SceneComponent",
    "Name": "SceneB394729846B2A972697D9FAD45A7D75B",
    "Outer": "BP_Brl_RoofRays01_C",
    "Properties": {
      "Mobility": "EComponentMobility::Static"
    }
  },
  {
    "Type": "SceneComponent",
    "Name": "SceneComponent_6",
    "Outer": "BP_Brl_RoofRays01_C"
  },
  {
    "Type": "SCS_Node",
    "Name": "SCS_Node_12",
    "Outer": "SimpleConstructionScript_4",
    "Properties": {
      "ComponentClass": {
        "ObjectName": "Class SceneComponent",
        "ObjectPath": "/Script/Engine"
      },
      "ComponentTemplate": {
        "ObjectName": "SceneComponent BP_Brl_RoofRays01_C:SceneB394729846B2A972697D9FAD45A7D75B",
        "ObjectPath": "DeadByDaylight/Content/Blueprints/Props/08-Boreal/BP_BRL_RoofRays01.2"
      },
      "ChildNodes": [
        {
          "ObjectName": "SCS_Node BP_Brl_RoofRays01_C:SimpleConstructionScript_4.SCS_Node_3",
          "ObjectPath": "DeadByDaylight/Content/Blueprints/Props/08-Boreal/BP_BRL_RoofRays01.5"
        }
      ],
      "VariableGuid": "41B143FF-4D8EA5FB-A2C0279D-65D30700",
      "InternalVariableName": "Scene"
    }
  },
  {
    "Type": "SCS_Node",
    "Name": "SCS_Node_3",
    "Outer": "SimpleConstructionScript_4",
    "Properties": {
      "ComponentClass": {
        "ObjectName": "Class StaticMeshComponent",
        "ObjectPath": "/Script/Engine"
      },
      "ComponentTemplate": {
        "ObjectName": "StaticMeshComponent BP_Brl_RoofRays01_C:LightConeNormal_GEN_VARIABLE",
        "ObjectPath": "DeadByDaylight/Content/Blueprints/Props/08-Boreal/BP_BRL_RoofRays01.8"
      },
      "VariableGuid": "6A4F9729-46A240A2-36F6AAAD-3900C161",
      "InternalVariableName": "LightConeNormal"
    }
  },
  {
    "Type": "SCS_Node",
    "Name": "SCS_Node_47",
    "Outer": "SimpleConstructionScript_4",
    "Properties": {
      "ComponentClass": {
        "ObjectName": "Class SceneComponent",
        "ObjectPath": "/Script/Engine"
      },
      "ComponentTemplate": {
        "ObjectName": "SceneComponent BP_Brl_RoofRays01_C:SceneComponent_6",
        "ObjectPath": "DeadByDaylight/Content/Blueprints/Props/08-Boreal/BP_BRL_RoofRays01.3"
      },
      "VariableGuid": "0554C38E-436F4C6E-0ACBC5BA-6EDD7CDB",
      "InternalVariableName": "DefaultSceneRoot"
    }
  },
  {
    "Type": "SimpleConstructionScript",
    "Name": "SimpleConstructionScript_4",
    "Outer": "BP_Brl_RoofRays01_C",
    "Properties": {
      "RootNodes": [
        {
          "ObjectName": "SCS_Node BP_Brl_RoofRays01_C:SimpleConstructionScript_4.SCS_Node_12",
          "ObjectPath": "DeadByDaylight/Content/Blueprints/Props/08-Boreal/BP_BRL_RoofRays01.4"
        }
      ],
      "AllNodes": [
        {
          "ObjectName": "SCS_Node BP_Brl_RoofRays01_C:SimpleConstructionScript_4.SCS_Node_12",
          "ObjectPath": "DeadByDaylight/Content/Blueprints/Props/08-Boreal/BP_BRL_RoofRays01.4"
        },
        {
          "ObjectName": "SCS_Node BP_Brl_RoofRays01_C:SimpleConstructionScript_4.SCS_Node_3",
          "ObjectPath": "DeadByDaylight/Content/Blueprints/Props/08-Boreal/BP_BRL_RoofRays01.5"
        }
      ],
      "DefaultSceneRootNode": {
        "ObjectName": "SCS_Node BP_Brl_RoofRays01_C:SimpleConstructionScript_4.SCS_Node_47",
        "ObjectPath": "DeadByDaylight/Content/Blueprints/Props/08-Boreal/BP_BRL_RoofRays01.6"
      }
    }
  },
  {
    "Type": "StaticMeshComponent",
    "Name": "LightConeNormal_GEN_VARIABLE",
    "Outer": "BP_Brl_RoofRays01_C",
    "Properties": {
      "StaticMesh": {
        "ObjectName": "StaticMesh LightConeNormal",
        "ObjectPath": "DeadByDaylight/Content/Effects/Mesh/LightConeNormal.2"
      },
      "bUseDefaultCollision": false,
      "OverrideMaterials": [
        {
          "ObjectName": "MaterialInstanceConstant MI_BRL_LightCone_Smoke",
          "ObjectPath": "DeadByDaylight/Content/Effects/Materials/MI_BRL_LightCone_Smoke.0"
        }
      ],
      "DetailLevelBeforeCastShadows": "DM_MAX",
      "BodyInstance": {
        "ObjectType": "ECC_WorldStatic",
        "CollisionEnabled": "ECollisionEnabled::NoCollision",
        "CollisionProfileName": "NoCollision",
        "CollisionResponses": {
          "ResponseArray": [
            {
              "Channel": "WorldStatic",
              "Response": "ECR_Ignore"
            },
            {
              "Channel": "WorldDynamic",
              "Response": "ECR_Ignore"
            },
            {
              "Channel": "Pawn",
              "Response": "ECR_Ignore"
            },
            {
              "Channel": "Visibility",
              "Response": "ECR_Ignore"
            },
            {
              "Channel": "Camera",
              "Response": "ECR_Ignore"
            },
            {
              "Channel": "PhysicsBody",
              "Response": "ECR_Ignore"
            },
            {
              "Channel": "Vehicle",
              "Response": "ECR_Ignore"
            },
            {
              "Channel": "Destructible",
              "Response": "ECR_Ignore"
            },
            {
              "Channel": "EngineTraceChannel2",
              "Response": "ECR_Ignore"
            },
            {
              "Channel": "EngineTraceChannel3",
              "Response": "ECR_Ignore"
            },
            {
              "Channel": "EngineTraceChannel4",
              "Response": "ECR_Ignore"
            },
            {
              "Channel": "EngineTraceChannel5",
              "Response": "ECR_Ignore"
            },
            {
              "Channel": "EngineTraceChannel6",
              "Response": "ECR_Ignore"
            },
            {
              "Channel": "Interactable",
              "Response": "ECR_Ignore"
            },
            {
              "Channel": "Audio",
              "Response": "ECR_Ignore"
            },
            {
              "Channel": "Slasher",
              "Response": "ECR_Ignore"
            },
            {
              "Channel": "Spider",
              "Response": "ECR_Ignore"
            },
            {
              "Channel": "Traps",
              "Response": "ECR_Ignore"
            },
            {
              "Channel": "InteractionDetector",
              "Response": "ECR_Ignore"
            },
            {
              "Channel": "BlinkBlocker",
              "Response": "ECR_Ignore"
            },
            {
              "Channel": "Ground",
              "Response": "ECR_Ignore"
            }
          ]
        },
        "MassInKgOverride": 0.0
      },
      "RelativeRotation": {
        "Pitch": 47.450344,
        "Yaw": 167.1757,
        "Roll": 53.04655
      },
      "RelativeScale3D": {
        "X": 0.3765653,
        "Y": 0.15,
        "Z": 0.2
      },
      "Mobility": "EComponentMobility::Static",
      "DetailModeBitMask": -5
    }
  }
]