[
  {
    "ExportType": "BodySetup",
    "ExportValue": {
      "AggGeom": {
        "SphylElems": [
          {
            "Center": {
              "X": -5.3348255,
              "Y": -2.3526812,
              "Z": 38.98463
            },
            "Rotation": {
              "Pitch": 0.0,
              "Yaw": 0.0,
              "Roll": 0.0
            },
            "Radius": 24.946375,
            "Length": 42.391262,
            "RestOffset": 0.0,
            "Name": "None",
            "bContributeToMass": true
          }
        ]
      },
      "WalkableSlopeOverride": {
        "WalkableSlopeBehavior": 85
      },
      "DefaultInstance": {
        "ObjectType": 29,
        "CollisionProfileName": "BlockAll",
        "CollisionResponses": {
          "ResponseArray": [
            {
              "Channel": "Interactable",
              "Response": 32
            },
            {
              "Channel": "Slasher",
              "Response": 32
            },
            {
              "Channel": "Blood",
              "Response": 32
            },
            {
              "Channel": "InteractionDetector",
              "Response": 33
            },
            {
              "Channel": "BlinkBlocker",
              "Response": 33
            },
            {
              "Channel": "Ground",
              "Response": 33
            },
            {
              "Channel": "Walkable",
              "Response": 32
            }
          ]
        }
      }
    }
  },
  {
    "ExportType": "NavCollision",
    "ExportValue": {}
  },
  {
    "ExportType": "StaticMesh",
    "ExportValue": {
      "MinLOD": {
        "Default": 0
      },
      "StaticMaterials": [
        {
          "MaterialInterface": {
            "ObjectName": "MI_HexTotem01",
            "OuterIndex": {
              "ObjectName": "/Game/Materials/Instances/MI_HexTotem01",
              "OuterIndex": 0
            }
          },
          "MaterialSlotName": "MI_HexTotem01",
          "ImportedMaterialSlotName": "MI_HexTotem01",
          "UVChannelData": {
            "bInitialized": true,
            "bOverrideDensities": false,
            "LocalUVDensities": 77.77674,
            "LocalUVDensities_NK01": 78.71875,
            "LocalUVDensities_NK02": 0.0,
            "LocalUVDensities_NK03": 0.0
          }
        }
      ],
      "LightmapUVDensity": 78.71875,
      "LightMapResolution": 64,
      "LightMapCoordinateIndex": 1,
      "LODForCollision": 2,
      "ExtendedBounds": {
        "Origin": {
          "X": -3.4428349,
          "Y": 0.6115341,
          "Z": 41.178085
        },
        "BoxExtent": {
          "X": 26.774076,
          "Y": 21.916878,
          "Z": 42.748913
        },
        "SphereRadius": 47.595867
      }
    }
  }
]