[
  {
    "Type": "DataTable",
    "Name": "TunableValuesDB",
    "Class": "UScriptClass'DataTable'",
    "Properties": {
      "RowStruct": {
        "ObjectName": "Class'TunableValue'",
        "ObjectPath": "/Script/DeadByDaylight"
      }
    },
    "Rows": {
      "BlinkChargeable_SecondsToCharge": {
        "Value": 2.0,
        "Description": "Time required to charge up the blinker to max range"
      },
      "SlasherNurseBlinkStunTimer": {
        "Value": 0.0,
        "Description": "How long the stun remains in queue for Nurse during Blink. 0 = Not queue"
      },
      "SlasherBlinkSpeedMultiplier": {
        "Value": 0.4,
        "Description": "Speed multiplier while chain blinking. 0 means unable to move"
      },
      "BlinkAttackHemorrhageDuration": {
        "Value": 30.0,
        "Description": "Duration of Hemorrhage status effect after blink attack"
      }
    }
  }
]