[
  {
    "ExportType": "Function",
    "ExportValue": {}
  },
  {
    "ExportType": "Function",
    "ExportValue": {}
  },
  {
    "ExportType": "Function",
    "ExportValue": {}
  },
  {
    "ExportType": "Function",
    "ExportValue": {}
  },
  {
    "ExportType": "Function",
    "ExportValue": {}
  },
  {
    "ExportType": "Function",
    "ExportValue": {}
  },
  {
    "ExportType": "Function",
    "ExportValue": {}
  },
  {
    "ExportType": "Function",
    "ExportValue": {}
  },
  {
    "ExportType": "Function",
    "ExportValue": {}
  },
  {
    "ExportType": "BlueprintGeneratedClass",
    "ExportValue": {
      "UberGraphFunction": 1
    }
  },
  {
    "ExportType": "Untrap",
    "ExportValue": {
      "UberGraphFrame": {},
      "StopInteractionOnChargeComplete": true,
      "InteractionID": "Untrap",
      "StopEnterMontageOnExit": false,
      "StopUpdateMontageOnExit": true,
      "SnapPosition": true,
      "SnapRotation": true,
      "ScaleMainAnimationToTime": true,
      "SnapBackType": "ESnapBackType::Always",
      "UseStartSnapTimeForSnapExitTime": true,
      "CancelOnHit": true,
      "InteractionTime": 5.3,
      "InteractionDescriptionText": {
        "Namespace": "",
        "Key": "DFCB8BAD403101F88986ECA3C217EEF1",
        "SourceString": "Untrap"
      },
      "UpdateMontage": {
        "MontageID": "BearTrapOpen"
      },
      "_tags": [
        "Semantics.Interaction.Id.Survivor.Untrapping"
      ]
    }
  }
]