[
  {
    "Type": "Texture2D",
    "Name": "statusBg",
    "Properties": {
      "Mips": [
        {
          "BulkData": {
            "BulkDataFlag": "BULKDATA_ForceInlinePayload",
            "ElementCount": 65536,
            "SizeOnDisk": 65536,
            "OffsetInFile": "0x10A60"
          },
          "SizeX": 256,
          "SizeY": 256,
          "SizeZ": 1
        }
      ],
      "FirstMip": 0,
      "SizeX": 256,
      "SizeY": 256,
      "NumSlices": 1,
      "IsVirtual": false,
      "Format": "PF_DXT5",
      "AddressX": "TA_Clamp",
      "AddressY": "TA_Clamp",
      "ImportedSize": {
        "X": 256,
        "Y": 256
      },
      "LightingGuid": "E0456BBE-44582403-23E615AF-DB6EEF69",
      "LODGroup": "TEXTUREGROUP_UI",
      "SRGB": false,
      "NeverStream": true
    }
  }
]